api_cli.py
dsframework/__init__.py
dsframework/base/__init__.py
dsframework/base/batch/__init__.py
dsframework/base/batch/dag_base.py
dsframework/base/batch/stage_base.py
dsframework/base/batch/workflow_base.py
dsframework/base/cloud_eval/__init__.py
dsframework/base/cloud_eval/cloud_eval_client_base.py
dsframework/base/cloud_eval/worker.py
dsframework/base/common/__init__.py
dsframework/base/common/__shared_data.py
dsframework/base/common/component.py
dsframework/base/common/functions.py
dsframework/base/common/object.py
dsframework/base/common/regex_handler.py
dsframework/base/deploy_scripts/build_and_register_image_in_devland.sh
dsframework/base/deploy_scripts/gae_devland_build_and_deploy.sh
dsframework/base/deploy_scripts/gke_build_and_deploy.sh
dsframework/base/deploy_scripts/gae/deploy-gae-devland.sh
dsframework/base/deploy_scripts/gke/create_gke_cluster.sh
dsframework/base/deploy_scripts/gke/deploy_app_to_gke_devland.sh
dsframework/base/deploy_scripts/gke/deploy_update_to_gke_devland.sh
dsframework/base/deploy_scripts/helper/devland_cleanup.sh
dsframework/base/deploy_scripts/helper/init_build_machine.sh
dsframework/base/deploy_scripts/helper/init_gc_repo.sh
dsframework/base/pipeline/__init__.py
dsframework/base/pipeline/pipeline.py
dsframework/base/pipeline/artifacts/__init__.py
dsframework/base/pipeline/artifacts/shared_artifacts.py
dsframework/base/pipeline/forcers/__init__.py
dsframework/base/pipeline/postprocessor/__init__.py
dsframework/base/pipeline/postprocessor/postprocess.py
dsframework/base/pipeline/predictables/__init__.py
dsframework/base/pipeline/predictables/predictable.py
dsframework/base/pipeline/predictors/__init__.py
dsframework/base/pipeline/preprocessor/__init__.py
dsframework/base/pipeline/preprocessor/preprocess.py
dsframework/base/server/__init__.py
dsframework/base/testable/__init__.py
dsframework/base/tester/__init__.py
dsframework/base/tester/evaluator_logic.py
dsframework/base/tester/tester_logic.py
dsFrameworkC-0.0.8.dist-info/METADATA
dsFrameworkC-0.0.8.dist-info/WHEEL
dsFrameworkC-0.0.8.dist-info/entry_points.txt
dsFrameworkC-0.0.8.dist-info/top_level.txt
dsFrameworkC-0.0.8.dist-info/RECORD
