Metadata-Version: 2.1
Name: dsFrameworkC
Version: 0.0.8
Summary: Data science framework library
Home-page: UNKNOWN
Author: oribrau@gmail.com
License: MIT
Platform: UNKNOWN
Requires-Python: >=3.6
Requires-Dist: click (==8.0.1)
Requires-Dist: pydantic (==1.8.2)
Requires-Dist: tldextract (==3.1.2)
Requires-Dist: uvicorn (==0.15.0)
Requires-Dist: gunicorn (==20.1.0)
Requires-Dist: fastapi (==0.68.1)
Requires-Dist: requests (==2.25.0)
Requires-Dist: unidecode (==1.1.1)
Requires-Dist: python-json-logger (==2.0.1)
Requires-Dist: google-api-python-client (==1.12.3)
Requires-Dist: oauth2client (==3.0.0)
Requires-Dist: pandas (<1.4.0,>=0.17.0)
Requires-Dist: boto3 (==1.17.12)
Requires-Dist: botocore (==1.20.12)
Requires-Dist: logdecorator (==2.2)
Requires-Dist: ujson (==4.3.0)
Requires-Dist: black
